django_curtail_uuid/__init__.py
django_curtail_uuid/curtail_uuid.py
django_curtail_uuid-1.0.4.dist-info/DESCRIPTION.rst
django_curtail_uuid-1.0.4.dist-info/METADATA
django_curtail_uuid-1.0.4.dist-info/RECORD
django_curtail_uuid-1.0.4.dist-info/WHEEL
django_curtail_uuid-1.0.4.dist-info/metadata.json
django_curtail_uuid-1.0.4.dist-info/top_level.txt
