Metadata-Version: 2.0
Name: django-curtail-uuid
Version: 1.0.4
Summary: Curtail UUID Appointed Length
Home-page: https://github.com/Brightcells/django-curtail-uuid
Author: Hackathon
Author-email: kimi.huang@brightcells.com
License: UNKNOWN
Keywords: django-curtail-uuid
Platform: UNKNOWN
Classifier: Development Status :: 5 - Production/Stable
Classifier: Environment :: Web Environment
Classifier: Framework :: Django
Classifier: Intended Audience :: Developers
Classifier: Programming Language :: Python
Classifier: Topic :: Software Development :: Libraries :: Python Modules
Classifier: Topic :: Office/Business :: Financial :: Spreadsheet
Requires-Dist: shortuuid
